azureml/__init__.py
azureml/designer/__init__.py
azureml/designer/modules/__init__.py
azureml/designer/modules/dl/__init__.py
azureml/designer/modules/dl/score/__init__.py
azureml/designer/modules/dl/score/constants.py
azureml/designer/modules/dl/score/package_info.py
azureml/designer/modules/dl/score/schema.py
azureml/designer/modules/dl/score/score_image_model/__init__.py
azureml/designer/modules/dl/score/score_image_model/module_invoker.py
azureml/designer/modules/dl/score/score_image_model/score_image_model.py
azureml_designer_score_modules-0.0.16.dist-info/METADATA
azureml_designer_score_modules-0.0.16.dist-info/WHEEL
azureml_designer_score_modules-0.0.16.dist-info/entry_points.txt
azureml_designer_score_modules-0.0.16.dist-info/top_level.txt
azureml_designer_score_modules-0.0.16.dist-info/RECORD
