Metadata-Version: 2.1
Name: azureml-designer-score-modules
Version: 0.0.16
Summary: UNKNOWN
Home-page: UNKNOWN
Author: Microsoft Crop
License: UNKNOWN
Platform: any
Classifier: Programming Language :: Python :: 3
Classifier: License :: Other/Proprietary License
Classifier: Operating System :: OS Independent
Requires-Python: >=3.6
Requires-Dist: azureml-designer-core[image,model] (==0.0.47)
Requires-Dist: azureml-designer-internal (==0.0.34)
Requires-Dist: click (==7.0)
